pgameplayer/__init__.py
pgameplayer/minimax_tree.py
pgameplayer/solvers/__init__.py
pgameplayer/solvers/connect4.py
pgameplayer/solvers/tictactoe.py
perfect_game_player-1.2.dist-info/LICENSE
perfect_game_player-1.2.dist-info/METADATA
perfect_game_player-1.2.dist-info/WHEEL
perfect_game_player-1.2.dist-info/top_level.txt
perfect_game_player-1.2.dist-info/RECORD
