Metadata-Version: 2.1
Name: perfect-game-player
Version: 1.2
Summary: Plays board games using Minimax algorithm
Home-page: https://github.com/dsaw/perfect-game-player
Author: Devesh Sawant
Author-email: devesh47cool@gmail.com
License: GPLv3
Platform: UNKNOWN
